{"nodes": [{"id": "scripts_python_src_theming_lib_contrast_py", "label": "contrast.py", "file_type": "code", "source_file": "Scripts/python/src/theming/lib/contrast.py", "source_location": "L1"}, {"id": "contrast_relative_luminance", "label": "relative_luminance()", "file_type": "code", "source_file": "Scripts/python/src/theming/lib/contrast.py", "source_location": "L11"}, {"id": "contrast_contrast_ratio", "label": "contrast_ratio()", "file_type": "code", "source_file": "Scripts/python/src/theming/lib/contrast.py", "source_location": "L37"}, {"id": "contrast_is_dark", "label": "is_dark()", "file_type": "code", "source_file": "Scripts/python/src/theming/lib/contrast.py", "source_location": "L52"}, {"id": "contrast_ensure_contrast", "label": "ensure_contrast()", "file_type": "code", "source_file": "Scripts/python/src/theming/lib/contrast.py", "source_location": "L57"}, {"id": "contrast_get_contrasting_color", "label": "get_contrasting_color()", "file_type": "code", "source_file": "Scripts/python/src/theming/lib/contrast.py", "source_location": "L114"}, {"id": "contrast_rationale_1", "label": "Contrast calculation utilities (WCAG luminance and contrast).  This module provi", "file_type": "rationale", "source_file": "Scripts/python/src/theming/lib/contrast.py", "source_location": "L1"}, {"id": "contrast_rationale_12", "label": "Calculate relative luminance per WCAG 2.1.      The formula converts sRGB to lin", "file_type": "rationale", "source_file": "Scripts/python/src/theming/lib/contrast.py", "source_location": "L12"}, {"id": "contrast_rationale_38", "label": "Calculate WCAG contrast ratio between two colors.      Returns a value between 1", "file_type": "rationale", "source_file": "Scripts/python/src/theming/lib/contrast.py", "source_location": "L38"}, {"id": "contrast_rationale_53", "label": "Determine if a color is perceptually dark.", "file_type": "rationale", "source_file": "Scripts/python/src/theming/lib/contrast.py", "source_location": "L53"}, {"id": "contrast_rationale_63", "label": "Adjust foreground color to meet minimum contrast ratio against background.", "file_type": "rationale", "source_file": "Scripts/python/src/theming/lib/contrast.py", "source_location": "L63"}, {"id": "contrast_rationale_115", "label": "Get a contrasting foreground color (black or white variant).", "file_type": "rationale", "source_file": "Scripts/python/src/theming/lib/contrast.py", "source_location": "L115"}], "edges": [{"source": "scripts_python_src_theming_lib_contrast_py", "target": "scripts_python_src_theming_lib_color_py", "relation": "imports_from", "confidence": "EXTRACTED", "source_file": "Scripts/python/src/theming/lib/contrast.py", "source_location": "L8", "weight": 1.0}, {"source": "scripts_python_src_theming_lib_contrast_py", "target": "contrast_relative_luminance", "relation": "contains", "confidence": "EXTRACTED", "source_file": "Scripts/python/src/theming/lib/contrast.py", "source_location": "L11", "weight": 1.0}, {"source": "scripts_python_src_theming_lib_contrast_py", "target": "contrast_contrast_ratio", "relation": "contains", "confidence": "EXTRACTED", "source_file": "Scripts/python/src/theming/lib/contrast.py", "source_location": "L37", "weight": 1.0}, {"source": "scripts_python_src_theming_lib_contrast_py", "target": "contrast_is_dark", "relation": "contains", "confidence": "EXTRACTED", "source_file": "Scripts/python/src/theming/lib/contrast.py", "source_location": "L52", "weight": 1.0}, {"source": "scripts_python_src_theming_lib_contrast_py", "target": "contrast_ensure_contrast", "relation": "contains", "confidence": "EXTRACTED", "source_file": "Scripts/python/src/theming/lib/contrast.py", "source_location": "L57", "weight": 1.0}, {"source": "scripts_python_src_theming_lib_contrast_py", "target": "contrast_get_contrasting_color", "relation": "contains", "confidence": "EXTRACTED", "source_file": "Scripts/python/src/theming/lib/contrast.py", "source_location": "L114", "weight": 1.0}, {"source": "contrast_contrast_ratio", "target": "contrast_relative_luminance", "relation": "calls", "confidence": "EXTRACTED", "source_file": "Scripts/python/src/theming/lib/contrast.py", "source_location": "L43", "weight": 1.0}, {"source": "contrast_is_dark", "target": "contrast_relative_luminance", "relation": "calls", "confidence": "EXTRACTED", "source_file": "Scripts/python/src/theming/lib/contrast.py", "source_location": "L54", "weight": 1.0}, {"source": "contrast_ensure_contrast", "target": "contrast_contrast_ratio", "relation": "calls", "confidence": "EXTRACTED", "source_file": "Scripts/python/src/theming/lib/contrast.py", "source_location": "L76", "weight": 1.0}, {"source": "contrast_ensure_contrast", "target": "contrast_is_dark", "relation": "calls", "confidence": "EXTRACTED", "source_file": "Scripts/python/src/theming/lib/contrast.py", "source_location": "L81", "weight": 1.0}, {"source": "contrast_get_contrasting_color", "target": "contrast_is_dark", "relation": "calls", "confidence": "EXTRACTED", "source_file": "Scripts/python/src/theming/lib/contrast.py", "source_location": "L116", "weight": 1.0}, {"source": "contrast_get_contrasting_color", "target": "contrast_ensure_contrast", "relation": "calls", "confidence": "EXTRACTED", "source_file": "Scripts/python/src/theming/lib/contrast.py", "source_location": "L123", "weight": 1.0}, {"source": "contrast_rationale_1", "target": "scripts_python_src_theming_lib_contrast_py", "relation": "rationale_for", "confidence": "EXTRACTED", "source_file": "Scripts/python/src/theming/lib/contrast.py", "source_location": "L1", "weight": 1.0}, {"source": "contrast_rationale_12", "target": "contrast_relative_luminance", "relation": "rationale_for", "confidence": "EXTRACTED", "source_file": "Scripts/python/src/theming/lib/contrast.py", "source_location": "L12", "weight": 1.0}, {"source": "contrast_rationale_38", "target": "contrast_contrast_ratio", "relation": "rationale_for", "confidence": "EXTRACTED", "source_file": "Scripts/python/src/theming/lib/contrast.py", "source_location": "L38", "weight": 1.0}, {"source": "contrast_rationale_53", "target": "contrast_is_dark", "relation": "rationale_for", "confidence": "EXTRACTED", "source_file": "Scripts/python/src/theming/lib/contrast.py", "source_location": "L53", "weight": 1.0}, {"source": "contrast_rationale_63", "target": "contrast_ensure_contrast", "relation": "rationale_for", "confidence": "EXTRACTED", "source_file": "Scripts/python/src/theming/lib/contrast.py", "source_location": "L63", "weight": 1.0}, {"source": "contrast_rationale_115", "target": "contrast_get_contrasting_color", "relation": "rationale_for", "confidence": "EXTRACTED", "source_file": "Scripts/python/src/theming/lib/contrast.py", "source_location": "L115", "weight": 1.0}]}